aiofoam/__init__.py
aiofoam/_cases.py
aiofoam/_cpus.py
aiofoam/_subprocess.py
aiofoam/py.typed
aiofoam-0.4.1.dist-info/LICENSE.txt
aiofoam-0.4.1.dist-info/METADATA
aiofoam-0.4.1.dist-info/WHEEL
aiofoam-0.4.1.dist-info/top_level.txt
aiofoam-0.4.1.dist-info/RECORD
